{
  "armor": {
    "acid": 0,
    "death": 2,
    "electricity": 0,
    "fire": 3,
    "frost": 2,
    "holy": 0,
    "parry": 0,
    "physical": 1,
    "poison": 0,
    "thorns": 0
  },
  "components": [
    "armor",
    "craftable",
    "glyph",
    "item",
    "minimap_pixel",
    "name",
    "position_2d",
    "value",
    "weight"
  ],
  "craftable": {
    "backgrounds": [],
    "biomes": [],
    "magic_slots": 3,
    "resource_types": [
      {
        "amount": 3,
        "id": 2
      }
    ],
    "time": 60,
    "tools": [
      14
    ]
  },
  "description": "A required item to properly challenge some popinjay to a duel.",
  "glyph": {
    "frames": [
      {
        "color": [
          255,
          255,
          255
        ],
        "delay": 0,
        "index": 374
      }
    ],
    "random_frame_start": false
  },
  "id": "193",
  "item": {
    "image": 95,
    "type": 11
  },
  "minimap_pixel": [
    122,
    93,
    57
  ],
  "name": "Leather Gloves",
  "value": 1500,
  "weight": 1.0
}