{
  "components": [
    "craftable",
    "glyph",
    "item",
    "minimap_pixel",
    "name",
    "position_2d",
    "stackable",
    "usable",
    "value",
    "weight"
  ],
  "craftable": {
    "backgrounds": [],
    "biomes": [],
    "magic_slots": 0,
    "resource_types": [
      {
        "amount": 1,
        "id": 3
      }
    ],
    "resources": [
      {
        "amount": 1,
        "id": "833"
      },
      {
        "amount": 1,
        "id": "core_2_Puffball_Mushroom"
      },
      {
        "amount": 1,
        "id": "core_2_Poppy_Seed"
      }
    ],
    "time": 20,
    "tools": [
      15
    ]
  },
  "description": "Explodindo no impacto, silenciando todos próximos por um curto período de tempo.",
  "glyph": {
    "frames": [
      {
        "color": [
          255,
          255,
          255
        ],
        "delay": 0,
        "index": 2949
      }
    ],
    "random_frame_start": false
  },
  "id": "core_2_Dust_Bomb",
  "item": {
    "image": 1335,
    "type": 17
  },
  "minimap_pixel": [
    194,
    133,
    109
  ],
  "name": "Bomba de Pó",
  "usable": {
    "ability": "core_2_Dust_Bomb",
    "recipe": ""
  },
  "value": 1500,
  "weight": 0.20000000298023224
}