{
  "components": [
    "craftable",
    "glyph",
    "item",
    "minimap_pixel",
    "name",
    "position_2d",
    "value",
    "weapon",
    "weight"
  ],
  "craftable": {
    "backgrounds": [],
    "biomes": [],
    "magic_slots": 1,
    "resource_types": [
      {
        "amount": 1,
        "id": 4
      }
    ],
    "time": 20,
    "tools": [
      12
    ]
  },
  "description": "Uma longa tira de material feita para proteger seus nós dos dedos em uma luta.",
  "glyph": {
    "frames": [
      {
        "color": [
          255,
          255,
          255
        ],
        "delay": 0,
        "index": 3003
      }
    ],
    "random_frame_start": false
  },
  "id": "core_2_Knuckle_Wrap",
  "item": {
    "image": 1387,
    "type": 13
  },
  "minimap_pixel": [
    156,
    160,
    161
  ],
  "name": "Faixa de Punho",
  "value": 400,
  "weapon": {
    "attack_speed": 0.800000011920929,
    "critical_hit": 0.0,
    "damage": [
      {
        "dmg_max": 4,
        "dmg_min": 1,
        "dmg_type": "physical"
      }
    ],
    "hands": 1,
    "hit_bonus": 0,
    "parry_bonus": 0,
    "range": 1,
    "type": 6
  },
  "weight": 0.5
}