{
  "ability_user": [
    "102",
    "104",
    "core_2_Rot"
  ],
  "artificial_intelligence": {
    "allies": [
      "4",
      "20"
    ],
    "allow_production": [],
    "behaviors": [],
    "enemies": [
      "9"
    ]
  },
  "components": [
    "ability_user",
    "actor",
    "artificial_intelligence",
    "collidable",
    "consumer",
    "dialogues",
    "equipment",
    "experience_gainer",
    "fighter",
    "glyph",
    "health",
    "humanoid",
    "minimap_pixel",
    "moveable",
    "name",
    "on_destruction",
    "persona",
    "position_2d",
    "resurrector",
    "sight",
    "skills",
    "stamina",
    "statistics",
    "tags"
  ],
  "corpse": "2514",
  "description": "",
  "dialogues": [
    "978",
    "979"
  ],
  "equipment": {
    "head_armor": [
      {
        "chance": 1.0,
        "id": "core_2_Bone_Crown",
        "name": "Coroa de Osso",
        "stack": 1
      }
    ],
    "right_hand": [
      {
        "chance": 1.0,
        "id": "381",
        "name": "Cajado de Cristal",
        "stack": 1
      }
    ],
    "torso_cloth": [
      {
        "chance": 1.0,
        "id": "776",
        "name": "Túnica de Couro",
        "stack": 1
      }
    ]
  },
  "experience_gainer": {
    "exp": 0,
    "level": 40
  },
  "fighter": {
    "attackNames": null
  },
  "glyph": {
    "frames": [
      {
        "color": [
          255,
          255,
          255
        ],
        "delay": 0,
        "index": 476
      }
    ],
    "random_frame_start": false
  },
  "health": 2300,
  "humanoid": {
    "race": "17"
  },
  "id": "core_2_Necrotyrant",
  "minimap_pixel": [
    224,
    172,
    105
  ],
  "moveable": {
    "speed": 0.699999988079071
  },
  "name": "Necrotirano",
  "on_destruction": {
    "abilities": [],
    "change_entities_globally": null,
    "change_weather": null,
    "destroy_entities_globally": [],
    "disable_day": false,
    "disable_fatigue": false,
    "disable_hearing": false,
    "disable_night": false,
    "drinkable_blood": false,
    "enable_teleport": false,
    "infinite_crafting_durability": false,
    "move_player": null,
    "recipes": [],
    "reduce_durability_globally": 0,
    "trigger_animation": "core_2_god_death",
    "trigger_weather": null,
    "trigger_weather_now": false
  },
  "persona": {
    "occupation": "Necrotirano"
  },
  "resurrector": {
    "delay": 20,
    "health_restore": 1.0
  },
  "sight": {
    "ignore_infra_penalty": false,
    "infravision": true,
    "range": 20,
    "threesixty": false
  },
  "skills": {
    "milestones": [
      "core_2_death_ray",
      "core_2_necrotic_touch",
      "core_2_raise_undead",
      "core_2_control_undead",
      "core_2_corpse_explosion"
    ],
    "skills": [
      "core_2_necromancy"
    ]
  },
  "stamina": {
    "fatigue": 100,
    "stamina": 100,
    "stamina_regen": 0.0
  },
  "statistics": {
    "dexterity": [
      80,
      89
    ],
    "endurance": [
      80,
      89
    ],
    "health_regen": 5.0,
    "intelligence": [
      120,
      130
    ],
    "magic_power": 10,
    "strength": [
      98,
      105
    ],
    "willpower": [
      120,
      130
    ]
  },
  "tags": [
    "20",
    "4",
    "27",
    "38"
  ]
}